pandas_td/__init__.py
pandas_td/ipython.py
pandas_td/notifier.py
pandas_td/queue.py
pandas_td/td.py
pandas_td/test_td.py
pandas_td/version.py
pandas_td/drivers/__init__.py
pandas_td/drivers/hipchat.py
pandas_td/drivers/slack.py
pandas_td-0.10.0.dist-info/LICENSE
pandas_td-0.10.0.dist-info/METADATA
pandas_td-0.10.0.dist-info/WHEEL
pandas_td-0.10.0.dist-info/top_level.txt
pandas_td-0.10.0.dist-info/RECORD
