Metadata-Version: 2.1
Name: pandas-td
Version: 0.10.0
Summary: Pandas extension for Treasure Data
Home-page: https://github.com/treasure-data/pandas-td
Author: Treasure Data, Inc.
Author-email: support@treasure-data.com
License: Apache License 2.0
Platform: Posix; MacOS X; Windows
Classifier: Development Status :: 4 - Beta
Classifier: Environment :: Console
Classifier: Framework :: IPython
Classifier: Intended Audience :: Developers
Classifier: License :: OSI Approved :: Apache Software License
Classifier: Operating System :: OS Independent
Classifier: Topic :: Software Development
Requires-Dist: certifi
Requires-Dist: pytz
Requires-Dist: tzlocal
Requires-Dist: futures (>=3.0.3)
Requires-Dist: six (>=1.9.0)
Requires-Dist: pandas (>=0.16.0)
Requires-Dist: requests (>=2.21.0)
Requires-Dist: td-client (>=0.4.0)
